.gitignore
.readthedocs.yaml
LICENSE
MANIFEST.in
README.md
lambdaPIC.svg
pyproject.toml
pytest.ini
setup.py
.github/workflows/python-publish.yml
docs/source/AI_prompt.md
docs/source/AI_prompt.rst
docs/source/api.rst
docs/source/callbacks.rst
docs/source/conda.yml
docs/source/conf.py
docs/source/core.rst
docs/source/example.rst
docs/source/extension.rst
docs/source/index.rst
docs/source/installation.rst
docs/source/introduction.rst
docs/source/simulation.rst
docs/source/species.rst
docs/source/write_callbacks.rst
docs/source/core/fields.rst
docs/source/core/particles.rst
example/laser-target-3d.py
example/laser-target.py
example/lwfa.py
example/photons.py
src/lambdapic/__init__.py
src/lambdapic/__main__.py
src/lambdapic/simulation.py
src/lambdapic/utils.py
src/lambdapic.egg-info/PKG-INFO
src/lambdapic.egg-info/SOURCES.txt
src/lambdapic.egg-info/dependency_links.txt
src/lambdapic.egg-info/entry_points.txt
src/lambdapic.egg-info/requires.txt
src/lambdapic.egg-info/top_level.txt
src/lambdapic/callback/__init__.py
src/lambdapic/callback/callback.py
src/lambdapic/callback/hdf5.py
src/lambdapic/callback/laser.py
src/lambdapic/callback/plot.py
src/lambdapic/callback/restart.py
src/lambdapic/callback/utils.py
src/lambdapic/callback/vtk.py
src/lambdapic/cli/__init__.py
src/lambdapic/cli/auto_reload.py
src/lambdapic/cli/main.py
src/lambdapic/cli/mcp.py
src/lambdapic/cli/mcp_manual.md
src/lambdapic/cli/stat.py
src/lambdapic/core/__init__.py
src/lambdapic/core/fields.py
src/lambdapic/core/particles.py
src/lambdapic/core/species.py
src/lambdapic/core/boundary/__init__.py
src/lambdapic/core/boundary/cpml.py
src/lambdapic/core/boundary/utils.py
src/lambdapic/core/collision/__init__.py
src/lambdapic/core/collision/collision.py
src/lambdapic/core/collision/cpu.py
src/lambdapic/core/collision/utils.py
src/lambdapic/core/current/__init__.py
src/lambdapic/core/current/cpu2d.c
src/lambdapic/core/current/cpu2d.pyi
src/lambdapic/core/current/cpu3d.c
src/lambdapic/core/current/cpu3d.pyi
src/lambdapic/core/current/deposition.py
src/lambdapic/core/interpolation/__init__.py
src/lambdapic/core/interpolation/cpu2d.c
src/lambdapic/core/interpolation/cpu2d.pyi
src/lambdapic/core/interpolation/cpu3d.c
