Metadata-Version: 2.4
Name: lambdapic
Version: 0.9.0
Summary: A Particle-in-Cell framework with dynamic behavior modification through callbacks
Author-email: xsgeng <xsgeng@siom.ac.cn>
Project-URL: Homepage, https://github.com/xsgeng/lambdapic
Keywords: Plasma Physics,Strong field,PIC
Classifier: Development Status :: 3 - Alpha
Classifier: Intended Audience :: Science/Research
Classifier: Programming Language :: Python :: 3.10
Requires-Python: >=3.10
License-File: LICENSE
Requires-Dist: numpy
Requires-Dist: numba
Requires-Dist: scipy
Requires-Dist: pydantic
Requires-Dist: tqdm
Requires-Dist: loguru
Requires-Dist: deprecated
Requires-Dist: mpi4py
Requires-Dist: pymetis; platform_system != "Windows"
Requires-Dist: impi_rt; platform_system == "Windows"
Requires-Dist: h5py
Requires-Dist: matplotlib
Requires-Dist: yaspin
Requires-Dist: packaging
Requires-Dist: requests
Requires-Dist: typer
Requires-Dist: threadpoolctl
Requires-Dist: dill
Provides-Extra: test
Requires-Dist: pytest>=7.0; extra == "test"
Requires-Dist: pytest-mpi>=0.6; extra == "test"
Requires-Dist: pytest-cov>=4.0; extra == "test"
Requires-Dist: pytest-xdist>=3.0; extra == "test"
Requires-Dist: codecov>=2.0; extra == "test"
Requires-Dist: mcp[cli]; extra == "test"
Provides-Extra: mcp
Requires-Dist: mcp[cli]; extra == "mcp"
Dynamic: license-file
